{"id":"ad5d789p1z8uu223odqx63k","title":"Lost Mine of Phandelver","desc":"","updated":1714897493975,"created":1709602797352,"custom":{},"fname":"Dimensional Mercenary.Lost Mine of Phandelver","type":"note","vault":{"fsPath":".","selfContained":true,"name":"Dendron-DnD"},"contentHash":"c5196963c0826ea0064e9bd236fbef12","links":[],"anchors":{"legend":{"type":"header","text":"Legend","value":"legend","line":8,"column":0,"depth":3},"characters":{"type":"header","text":"Characters","value":"characters","line":13,"column":0,"depth":2},"mission-incentives":{"type":"header","text":"Mission Incentives","value":"mission-incentives","line":28,"column":0,"depth":2},"introduction":{"type":"header","text":"Introduction","value":"introduction","line":32,"column":0,"depth":2},"delivery-to-phandalin":{"type":"header","text":"Delivery to Phandalin","value":"delivery-to-phandalin","line":37,"column":0,"depth":2},"cragmaw-cave":{"type":"header","text":"Cragmaw Cave","value":"cragmaw-cave","line":44,"column":0,"depth":2},"phandalin":{"type":"header","text":"Phandalin","value":"phandalin","line":62,"column":0,"depth":2},"old-owl-well":{"type":"header","text":"Old Owl Well","value":"old-owl-well","line":91,"column":0,"depth":2},"back-to-phandalin":{"type":"header","text":"Back to Phandalin","value":"back-to-phandalin","line":118,"column":0,"depth":2},"tresendar-manor":{"type":"header","text":"Tresendar Manor","value":"tresendar-manor","line":124,"column":0,"depth":2},"return-to-town":{"type":"header","text":"Return to town","value":"return-to-town","line":166,"column":0,"depth":2},"thundertree":{"type":"header","text":"Thundertree","value":"thundertree","line":191,"column":0,"depth":2},"connyberry":{"type":"header","text":"Connyberry","value":"connyberry","line":229,"column":0,"depth":2},"return-to-phandalin":{"type":"header","text":"Return to Phandalin","value":"return-to-phandalin","line":258,"column":0,"depth":2},"cragmaw-castle":{"type":"header","text":"Cragmaw Castle","value":"cragmaw-castle","line":267,"column":0,"depth":2},"back-to-phandalin-to-confront-iarno":{"type":"header","text":"Back to Phandalin to confront Iarno","value":"back-to-phandalin-to-confront-iarno","line":308,"column":0,"depth":2},"post-iarno-fight":{"type":"header","text":"Post-Iarno fight","value":"post-iarno-fight","line":330,"column":0,"depth":2},"wave-echo-cave":{"type":"header","text":"Wave Echo Cave","value":"wave-echo-cave","line":341,"column":0,"depth":2}},"children":[],"parent":"wh0tjc733o0zvtkcrjc06xb","data":{}}
